README.rst
setup.py
enum3field/__init__.py
enum3field.egg-info/PKG-INFO
enum3field.egg-info/SOURCES.txt
enum3field.egg-info/dependency_links.txt
enum3field.egg-info/top_level.txt