Metadata-Version: 1.0
Name: enum3field
Version: 0.1.1
Summary: A Django 1.7+ model field for use with Python 3 enums.
Home-page: https://github.com/joshdata/enum3field
Author: Joshua Tauberer
Author-email: jt@occams.info
License: CC0 (copyright waived)
Keywords: Django enum field
Platform: UNKNOWN
